pylinac/__init__.py
pylinac/acr.py
pylinac/cheese.py
pylinac/ct.py
pylinac/dlg.py
pylinac/field_analysis.py
pylinac/field_profile_analysis.py
pylinac/log_analyzer.py
pylinac/nuclear.py
pylinac/picketfence.py
pylinac/planar_imaging.py
pylinac/quart.py
pylinac/settings.py
pylinac/starshot.py
pylinac/version.py
pylinac/vmat.py
pylinac/winston_lutz.py
pylinac/calibration/__init__.py
pylinac/calibration/tg51.py
pylinac/calibration/trs398.py
pylinac/contrib/__init__.py
pylinac/contrib/orthogonality.py
pylinac/contrib/quasar.py
pylinac/core/__init__.py
pylinac/core/array_utils.py
pylinac/core/contrast.py
pylinac/core/decorators.py
pylinac/core/exceptions.py
pylinac/core/gamma.py
pylinac/core/geometry.py
pylinac/core/hill.py
pylinac/core/image.py
pylinac/core/io.py
pylinac/core/mask.py
pylinac/core/metrics.py
pylinac/core/mtf.py
pylinac/core/nps.py
pylinac/core/pdf.py
pylinac/core/plotly_utils.py
pylinac/core/profile.py
pylinac/core/roi.py
pylinac/core/scale.py
pylinac/core/typing.py
pylinac/core/utilities.py
pylinac/core/validators.py
pylinac/core/warnings.py
pylinac/core/image_generator/__init__.py
pylinac/core/image_generator/layers.py
pylinac/core/image_generator/simulators.py
pylinac/core/image_generator/utils.py
pylinac/files/Pylinac-GREEN.png
pylinac/metrics/__init__.py
pylinac/metrics/features.py
pylinac/metrics/image.py
pylinac/metrics/profile.py
pylinac/metrics/utils.py
pylinac/plan_generator/__init__.py
pylinac/plan_generator/dicom.py
pylinac/plan_generator/fluence.py
pylinac/plan_generator/mlc.py
pylinac-3.40.0.dist-info/METADATA
pylinac-3.40.0.dist-info/WHEEL
pylinac-3.40.0.dist-info/licenses/LICENSE.txt
pylinac-3.40.0.dist-info/RECORD
