Metadata-Version: 2.4
Name: pylinac
Version: 3.40.0
Summary: A toolkit for performing TG-142 QA-related tasks on a linear accelerator
Author-email: James Kerns <jkerns100@gmail.com>
License-Expression: MIT
License-File: LICENSE.txt
Keywords: TG-142,analysis,image,medical,physics
Classifier: Intended Audience :: Developers
Classifier: Intended Audience :: Healthcare Industry
Classifier: Intended Audience :: Science/Research
Classifier: License :: OSI Approved :: MIT License
Classifier: Natural Language :: English
Classifier: Programming Language :: Python
Classifier: Programming Language :: Python :: 3
Classifier: Topic :: Scientific/Engineering :: Image Recognition
Classifier: Topic :: Scientific/Engineering :: Medical Science Apps.
Classifier: Topic :: Scientific/Engineering :: Physics
Classifier: Topic :: Software Development :: Libraries
Requires-Python: >=3.9
Requires-Dist: argue~=0.3.1
Requires-Dist: eval-type-backport; python_version <= '3.9'
Requires-Dist: matplotlib>=3.0
Requires-Dist: numpy>=1.22
Requires-Dist: pillow>=4.0
Requires-Dist: plotly>=5.0
Requires-Dist: py-linq~=1.4.0
Requires-Dist: pydantic>=2.0
Requires-Dist: pydicom<3,>=2.0
Requires-Dist: quaac
Requires-Dist: reportlab>=3.3
Requires-Dist: scikit-image>=0.18; python_version < '3.13'
Requires-Dist: scikit-image>=0.25; python_version >= '3.13'
Requires-Dist: scipy>=1.11.0
Requires-Dist: tabulate~=0.9.0
Requires-Dist: tqdm>=3.8
Requires-Dist: typing-extensions>=4.14.1
Provides-Extra: developer
Requires-Dist: google-cloud-storage>=2.18.2; extra == 'developer'
Requires-Dist: hatch<2.0.0,>=1.14.0; extra == 'developer'
Requires-Dist: nox>=2024.4.15; extra == 'developer'
Requires-Dist: parameterized>=0.9.0; extra == 'developer'
Requires-Dist: pytest-cov>=5.0.0; extra == 'developer'
Requires-Dist: pytest-xdist>=3.6.1; extra == 'developer'
Requires-Dist: pytest>=8.3.2; extra == 'developer'
Provides-Extra: docs
Requires-Dist: autodoc-pydantic>=2.1.0; extra == 'docs'
Requires-Dist: furo>=2024.8.6; extra == 'docs'
Requires-Dist: sphinx-autobuild>=2021.3.14; extra == 'docs'
Requires-Dist: sphinx-copybutton>=0.5.2; extra == 'docs'
Requires-Dist: sphinx-design>=0.6.0; extra == 'docs'
Requires-Dist: sphinx>=7.1.2; extra == 'docs'
